atlasrun/__init__.py
atlasrun/cli.py
atlasrun/executor.py
atlasrun/db/__init__.py
atlasrun/db/connection.py
atlasrun/db/database.py
atlasrun/db/models.py
atlasrun/db/queries.py
atlasrun/db/updates.py
atlasrun/src/__init__.py
atlasrun/src/script_templates.py
atlasrun/src/task_display.py
atlasrun-0.1.0.dist-info/licenses/LICENSE
atlasrun-0.1.0.dist-info/METADATA
atlasrun-0.1.0.dist-info/WHEEL
atlasrun-0.1.0.dist-info/entry_points.txt
atlasrun-0.1.0.dist-info/top_level.txt
atlasrun-0.1.0.dist-info/RECORD
