Metadata-Version: 2.4
Name: atlasrun
Version: 0.1.0
Summary: A lightweight local task queue and execution manager for batch command-line jobs
Home-page: https://github.com/atlasbioinfo/atlasrun
Author: Haopeng Yu
Author-email: Haopeng Yu <atlasbioin4@gmail.com>
Maintainer-email: Haopeng Yu <atlasbioin4@gmail.com>
License: Apache-2.0
Project-URL: Homepage, https://github.com/your-username/atlasrun
Project-URL: Documentation, https://github.com/your-username/atlasrun#readme
Project-URL: Repository, https://github.com/your-username/atlasrun.git
Project-URL: Bug Tracker, https://github.com/your-username/atlasrun/issues
Keywords: task queue,command line,batch jobs,process management
Classifier: Development Status :: 4 - Beta
Classifier: Intended Audience :: Developers
Classifier: Intended Audience :: System Administrators
Classifier: License :: OSI Approved :: Apache Software License
Classifier: Operating System :: OS Independent
Classifier: Programming Language :: Python :: 3
Classifier: Programming Language :: Python :: 3.7
Classifier: Programming Language :: Python :: 3.8
Classifier: Programming Language :: Python :: 3.9
Classifier: Programming Language :: Python :: 3.10
Classifier: Programming Language :: Python :: 3.11
Classifier: Programming Language :: Python :: 3.12
Classifier: Topic :: System :: Systems Administration
Classifier: Topic :: Utilities
Requires-Python: >=3.7
License-File: LICENSE
Requires-Dist: tabulate>=0.9.0
Dynamic: author
Dynamic: home-page
Dynamic: license-file
Dynamic: requires-python
